Workbook

Sheet README
A1: AI 300 Assignment 3 | BrightPath chart workbook
A2: Fictional classroom example. BrightPath Retail and all figures are course practice data.
A4: Purpose: holds the data behind every chart in the packet. Edit a number on Chart_Data (or upstream) and the charts on the Charts sheet update.
A5: Sheets
A6: Raw_Data: the CSV exactly as supplied (23 rows, 14 columns). Only change: thousands separators removed so numbers are numeric. Includes the duplicate ST-112 row and the unreviewed AI columns.
A7: Clean_Data: 22 unique stores linked to Raw_Data by formula, with recalculated measures and a cohort flag. Duplicate row excluded; region label standardised. No source value overwritten.
A8: Chart_Data: the exact ranges each chart reads (V1 initial, V2 first revision, V3 final).
A9: Summary: reconciliations and the statistics quoted in the packet.
A10: Charts: three native Excel charts (V1, V2, V3).
A11: Colour legend
A12: Blue text = hardcoded input (raw data, thresholds). Green text = link to another sheet. Black text = calculation. Yellow fill = row with a data issue.
A13: Notes
... A18: Source: BrightPath_Store_Performance_Sample.csv and AI300 Business Analytics Reference Materials, Section 4 (course-supplied).

Sheet Raw_Data
A1: store_id | B1: region | C1: format | D1: sq_ft | E1: months_open | F1: labor_hours_weekly | G1: avg_weekly_units | H1: avg_weekly_revenue | I1: units_per_labor_hour | J1: stockout_rate_pct | K1: forecast_error_pct_prior_q | L1: forecast_error_pct_last_q | M1: ai_finding | N1: ai_recommendation
A2: ST-101 | B2: Pacific Northwest | C2: Full-line | D2: 32701 | E2: 96 | F2: 595 | G2: 2434 | H2: 83944 | I2: 4.1 | J2: 6.5 | K2: 5 | L2: 7.7 | M2: Forecast error above chain average | N2: Review demand inputs
A3: ST-102 | B3: Pacific Northwest | C3: Compact | D3: 12133 | E3: 130 | F3: 221 | G3: 749 | H3: 21902 | I3: 3.4 | J3: 5.5 | K3: 7.1 | L3: 6.9 | M3: Stockout rate above target | N3: Increase replenishment frequency
A4: ST-103 | B4: Pacific NW | C4: Outlet | D4: 17844 | E4: 52 | F4: 324 | G4: 1672 | H4: 36193 | I4: 5.2 | J4: 2.5 | K4: 7 | L4: 6.9 | N4: No action
A5: ST-104 | B5: Mountain | C5: Compact | D5: 11864 | E5: 4 | F5: 216 | G5: 527 | H5: 15695 | I5: 2.4 | J5: 2.4 | K5: 6.3 | L5: 3.8 | M5: Productivity above chain average | N5: Study and document practice
A6: ST-105 | B6: Mountain | C6: Compact | D6: 10351 | E6: 7 | F6: 188 | G6: 560 | H6: 15789 | I6: 3 | J6: 8.3 | K6: 8.3 | L6: 4.5 | M6: Compact format underperforms in the Mountain region | N6: Convert Mountain Compact stores to Full-line
A7: ST-106 | B7: Mountain | C7: Compact | D7: 12649 | E7: 9 | F7: 230 | G7: 708 | H7: 19983 | I7: 6.8 | J7: 2 | K7: 6.5 | L7: 4.6 | N7: No action
A8: ST-107 | B8: Mountain | C8: Full-line | D8: 25739 | E8: 88 | F8: 468 | G8: 2012 | H8: 66538 | I8: 4.3 | J8: 8.5 | K8: 5.2 | L8: 9 | N8: No action
A9: ST-108 | B9: Southwest | C9: Full-line | D9: 27939 | E9: 112 | F9: 508 | G9: 2113 | H9: 71701 | I9: 4.2 | J9: 1.6 | K9: 8.4 | L9: 7.5 | M9: Service levels at risk | N9: Add 40 labour hours a week
A10: ST-109 | B10: Southwest | C10: Compact | D10: 10941 | E10: 68 | F10: 199 | G10: 718 | H10: 20039 | I10: 3.6 | J10: 8.4 | K10: 7.6 | L10: 4.2 | N10: No action
A11: ST-110 | B11: Southwest | C11: Outlet | D11: 18566 | E11: 44 | F11: 338 | G11: 1839 | H11: 573768 | I11: 5.4 | J11: 6.9 | K11: 6.6 | L11: 5.8 | N11: No action
A12: ST-111 | B12: Midwest | C12: Full-line | D12: 27096 | E12: 143 | F12: 493 | G12: 2090 | H12: 75305 | I12: 4.2 | J12: 2.3 | K12: 8.1 | L12: 4.7 | N12: No action
A13: ST-112 | B13: Midwest | C13: Compact | D13: 10196 | E13: 102 | F13: 185 | G13: 677 | H13: 20522 | I13: 3.7 | J13: 3 | K13: 3.7 | L13: 6.1 | N13: No action
A14: ST-112 | B14: Midwest | C14: Compact | D14: 10196 | E14: 102 | F14: 185 | G14: 677 | H14: 20522 | I14: 3.7 | J14: 3 | K14: 3.7 | L14: 6.1 | N14: No action | O14: <- duplicate of row 13
A15: ST-113 | B15: Midwest | C15: Outlet | D15: 21882 | E15: 66 | F15: 398 | G15: 2022 | H15: 40482 | I15: 5.1 | J15: 3.8 | K15: 5.6 | L15: 8.2 | N15: No action
A16: ST-114 | B16: Midwest | C16: Full-line | D16: 26981 | E16: 3 | F16: 491 | G16: 2018 | H16: 70209 | I16: 4.1 | J16: 3.1 | K16: 5.3 | L16: 8.7 | M16: Down 14 percent against the same quarter last year | N16: Investigate assortment
A17: ST-115 | B17: Northeast | C17: Full-line | D17: 32602 | E17: 156 | F17: 593 | G17: 2384 | H17: 81269 | I17: 4 | J17: 8.1 | K17: 7.3 | L17: 7.9 | N17: No action
A18: ST-116 | B18: Northeast | C18: Compact | D18: 9615 | E18: 84 | F18: 175 | G18: 656 | H18: 18057 | I18: 3.8 | J18: 4.9 | K18: 3.4 | L18: 5 | N18: No action
A19: ST-117 | B19: Northeast | C19: Outlet | D19: 20389 | E19: 71 | F19: 371 | G19: 1881 | H19: 41627 | I19: 5.1 | J19: 1.3 | K19: 6.2 | L19: 11.4 | M19: Forecast accuracy improved quarter over quarter | N19: Extend the current forecast method
A20: ST-118 | B20: Northeast | C20: Compact | D20: 9526 | E20: 47 | F20: 173 | G20: 661 | H20: 18254 | I20: 3.8 | J20: 8.1 | K20: 5.3 | L20: 3.9 | N20: No action
A21: ST-119 | B21: Southeast | C21: Full-line | D21: 25116 | E21: 91 | F21: 457 | G21: 1842 | H21: 63338 | I21: 4 | J21: 8.4 | K21: 4.8 | L21: 5.9 | N21: No action
A22: ST-120 | B22: Southeast | C22: Compact | E22: 55 | F22: 234 | G22: 842 | H22: 23885 | I22: 3.6 | J22: 6.9 | K22: 4.2 | L22: 9.8 | M22: Sales per square foot in the bottom decile | N22: Review space allocation
A23: ST-121 | B23: Southeast | C23: Outlet | D23: 19981 | E23: 39 | F23: 363 | G23: 1931 | H23: 38277 | I23: 5.3 | J23: 1.6 | K23: 6.7 | L23: 9.9 | M23: Low total revenue relative to the chain | N23: Recommend closure at lease end
A24: ST-122 | B24: Southeast | C24: Full-line | D24: 33561 | E24: 128 | F24: 610 | G24: 2568 | H24: 88236 | I24: 4.2 | J24: 104 | K24: 5.8 | L24: 4.7 | N24: No action
A26: Untouched copy of the supplied CSV (numeric conversion only). Row 14 repeats ST-112 (exact duplicate).

Sheet Clean_Data
A1: store_id | B1: region_raw | C1: region_clean | D1: format | E1: sq_ft | F1: months_open | G1: labor_hours_weekly | H1: avg_weekly_units | I1: avg_weekly_revenue | J1: reported_units_per_labor_hour | K1: stockout_rate_pct | L1: forecast_error_prior_q | M1: forecast_error_last_q | N1: recalc_units_per_labor_hour | O1: revenue_per_labor_hour | P1: revenue_per_unit | Q1: reported_minus_recalc | R1: cohort | S1: data_note
A2: =Raw_Data!A2 -> ST-101 | B2: =Raw_Data!B2 -> Pacific Northwest | C2: =IF(B2="Pacific NW","Pacific Northwest",B2) -> Pacific Northwest | D2: =Raw_Data!C2 -> Full-line | E2: =IF(Raw_Data!D2="","",Raw_Data!D2) -> 32701 | F2: =Raw_Data!E2 -> 96 | G2: =Raw_Data!F2 -> 595 | H2: =Raw_Data!G2 -> 2434 | I2: =Raw_Data!H2 -> 83944 | J2: =Raw_Data!I2 -> 4.1 | K2: =Raw_Data!J2 -> 6.5 | L2: =Raw_Data!K2 -> 5 | M2: =Raw_Data!L2 -> 7.7 | N2: =H2/G2 -> 4.0907563 | O2: =I2/G2 -> 141.08235 | P2: =I2/H2 -> 34.488085 | Q2: =J2-N2 -> 0.0092436975 | R2: =IF(F2<13,"Young (<13 mo)","Mature (13+ mo)") -> Mature (13+ mo)
A3: =Raw_Data!A3 -> ST-102 | B3: =Raw_Data!B3 -> Pacific Northwest | C3: =IF(B3="Pacific NW","Pacific Northwest",B3) -> Pacific Northwest | D3: =Raw_Data!C3 -> Compact | E3: =IF(Raw_Data!D3="","",Raw_Data!D3) -> 12133 | F3: =Raw_Data!E3 -> 130 | G3: =Raw_Data!F3 -> 221 | H3: =Raw_Data!G3 -> 749 | I3: =Raw_Data!H3 -> 21902 | J3: =Raw_Data!I3 -> 3.4 | K3: =Raw_Data!J3 -> 5.5 | L3: =Raw_Data!K3 -> 7.1 | M3: =Raw_Data!L3 -> 6.9 | N3: =H3/G3 -> 3.3891403 | O3: =I3/G3 -> 99.104072 | P3: =I3/H3 -> 29.241656 | Q3: =J3-N3 -> 0.010859729 | R3: =IF(F3<13,"Young (<13 mo)","Mature (13+ mo)") -> Mature (13+ mo)
A4: =Raw_Data!A4 -> ST-103 | B4: =Raw_Data!B4 -> Pacific NW | C4: =IF(B4="Pacific NW","Pacific Northwest",B4) -> Pacific Northwest | D4: =Raw_Data!C4 -> Outlet | E4: =IF(Raw_Data!D4="","",Raw_Data!D4) -> 17844 | F4: =Raw_Data!E4 -> 52 | G4: =Raw_Data!F4 -> 324 | H4: =Raw_Data!G4 -> 1672 | I4: =Raw_Data!H4 -> 36193 | J4: =Raw_Data!I4 -> 5.2 | K4: =Raw_Data!J4 -> 2.5 | L4: =Raw_Data!K4 -> 7 | M4: =Raw_Data!L4 -> 6.9 | N4: =H4/G4 -> 5.1604938 | O4: =I4/G4 -> 111.70679 | P4: =I4/H4 -> 21.646531 | Q4: =J4-N4 -> 0.039506173 | R4: =IF(F4<13,"Young (<13 mo)","Mature (13+ mo)") -> Mature (13+ mo) | S4: Region label "Pacific NW" standardised
A5: =Raw_Data!A5 -> ST-104 | B5: =Raw_Data!B5 -> Mountain | C5: =IF(B5="Pacific NW","Pacific Northwest",B5) -> Mountain | D5: =Raw_Data!C5 -> Compact | E5: =IF(Raw_Data!D5="","",Raw_Data!D5) -> 11864 | F5: =Raw_Data!E5 -> 4 | G5: =Raw_Data!F5 -> 216 | H5: =Raw_Data!G5 -> 527 | I5: =Raw_Data!H5 -> 15695 | J5: =Raw_Data!I5 -> 2.4 | K5: =Raw_Data!J5 -> 2.4 | L5: =Raw_Data!K5 -> 6.3 | M5: =Raw_Data!L5 -> 3.8 | N5: =H5/G5 -> 2.4398148 | O5: =I5/G5 -> 72.662037 | P5: =I5/H5 -> 29.781784 | Q5: =J5-N5 -> -0.039814815 | R5: =IF(F5<13,"Young (<13 mo)","Mature (13+ mo)") -> Young (<13 mo)
A6: =Raw_Data!A6 -> ST-105 | B6: =Raw_Data!B6 -> Mountain | C6: =IF(B6="Pacific NW","Pacific Northwest",B6) -> Mountain | D6: =Raw_Data!C6 -> Compact | E6: =IF(Raw_Data!D6="","",Raw_Data!D6) -> 10351 | F6: =Raw_Data!E6 -> 7 | G6: =Raw_Data!F6 -> 188 | H6: =Raw_Data!G6 -> 560 | I6: =Raw_Data!H6 -> 15789 | J6: =Raw_Data!I6 -> 3 | K6: =Raw_Data!J6 -> 8.3 | L6: =Raw_Data!K6 -> 8.3 | M6: =Raw_Data!L6 -> 4.5 | N6: =H6/G6 -> 2.9787234 | O6: =I6/G6 -> 83.984043 | P6: =I6/H6 -> 28.194643 | Q6: =J6-N6 -> 0.021276596 | R6: =IF(F6<13,"Young (<13 mo)","Mature (13+ mo)") -> Young (<13 mo)
A7: =Raw_Data!A7 -> ST-106 | B7: =Raw_Data!B7 -> Mountain | C7: =IF(B7="Pacific NW","Pacific Northwest",B7) -> Mountain | D7: =Raw_Data!C7 -> Compact | E7: =IF(Raw_Data!D7="","",Raw_Data!D7) -> 12649 | F7: =Raw_Data!E7 -> 9 | G7: =Raw_Data!F7 -> 230 | H7: =Raw_Data!G7 -> 708 | I7: =Raw_Data!H7 -> 19983 | J7: =Raw_Data!I7 -> 6.8 | K7: =Raw_Data!J7 -> 2 | L7: =Raw_Data!K7 -> 6.5 | M7: =Raw_Data!L7 -> 4.6 | N7: =H7/G7 -> 3.0782609 | O7: =I7/G7 -> 86.882609 | P7: =I7/H7 -> 28.224576 | Q7: =J7-N7 -> 3.7217391 | R7: =IF(F7<13,"Young (<13 mo)","Mature (13+ mo)") -> Young (<13 mo) | S7: Reported 6.8 does not match units/hours (3.08)
A8: =Raw_Data!A8 -> ST-107 | B8: =Raw_Data!B8 -> Mountain | C8: =IF(B8="Pacific NW","Pacific Northwest",B8) -> Mountain | D8: =Raw_Data!C8 -> Full-line | E8: =IF(Raw_Data!D8="","",Raw_Data!D8) -> 25739 | F8: =Raw_Data!E8 -> 88 | G8: =Raw_Data!F8 -> 468 | H8: =Raw_Data!G8 -> 2012 | I8: =Raw_Data!H8 -> 66538 | J8: =Raw_Data!I8 -> 4.3 | K8: =Raw_Data!J8 -> 8.5 | L8: =Raw_Data!K8 -> 5.2 | M8: =Raw_Data!L8 -> 9 | N8: =H8/G8 -> 4.2991453 | O8: =I8/G8 -> 142.17521 | P8: =I8/H8 -> 33.070577 | Q8: =J8-N8 -> 0.00085470085 | R8: =IF(F8<13,"Young (<13 mo)","Mature (13+ mo)") -> Mature (13+ mo)
A9: =Raw_Data!A9 -> ST-108 | B9: =Raw_Data!B9 -> Southwest | C9: =IF(B9="Pacific NW","Pacific Northwest",B9) -> Southwest | D9: =Raw_Data!C9 -> Full-line | E9: =IF(Raw_Data!D9="","",Raw_Data!D9) -> 27939 | F9: =Raw_Data!E9 -> 112 | G9: =Raw_Data!F9 -> 508 | H9: =Raw_Data!G9 -> 2113 | I9: =Raw_Data!H9 -> 71701 | J9: =Raw_Data!I9 -> 4.2 | K9: =Raw_Data!J9 -> 1.6 | L9: =Raw_Data!K9 -> 8.4 | M9: =Raw_Data!L9 -> 7.5 | N9: =H9/G9 -> 4.1594488 | O9: =I9/G9 -> 141.1437 | P9: =I9/H9 -> 33.93327 | Q9: =J9-N9 -> 0.040551181 | R9: =IF(F9<13,"Young (<13 mo)","Mature (13+ mo)") -> Mature (13+ mo)
A10: =Raw_Data!A10 -> ST-109 | B10: =Raw_Data!B10 -> Southwest | C10: =IF(B10="Pacific NW","Pacific Northwest",B10) -> Southwest | D10: =Raw_Data!C10 -> Compact | E10: =IF(Raw_Data!D10="","",Raw_Data!D10) -> 10941 | F10: =Raw_Data!E10 -> 68 | G10: =Raw_Data!F10 -> 199 | H10: =Raw_Data!G10 -> 718 | I10: =Raw_Data!H10 -> 20039 | J10: =Raw_Data!I10 -> 3.6 | K10: =Raw_Data!J10 -> 8.4 | L10: =Raw_Data!K10 -> 7.6 | M10: =Raw_Data!L10 -> 4.2 | N10: =H10/G10 -> 3.6080402 | O10: =I10/G10 -> 100.69849 | P10: =I10/H10 -> 27.909471 | Q10: =J10-N10 -> -0.008040201 | R10: =IF(F10<13,"Young (<13 mo)","Mature (13+ mo)") -> Mature (13+ mo)
A11: =Raw_Data!A11 -> ST-110 | B11: =Raw_Data!B11 -> Southwest | C11: =IF(B11="Pacific NW","Pacific Northwest",B11) -> Southwest | D11: =Raw_Data!C11 -> Outlet | E11: =IF(Raw_Data!D11="","",Raw_Data!D11) -> 18566 | F11: =Raw_Data!E11 -> 44 | G11: =Raw_Data!F11 -> 338 | H11: =Raw_Data!G11 -> 1839 | I11: =Raw_Data!H11 -> 573768 | J11: =Raw_Data!I11 -> 5.4 | K11: =Raw_Data!J11 -> 6.9 | L11: =Raw_Data!K11 -> 6.6 | M11: =Raw_Data!L11 -> 5.8 | N11: =H11/G11 -> 5.4408284 | O11: =I11/G11 -> 1697.5385 | P11: =I11/H11 -> 312 | Q11: =J11-N11 -> -0.040828402 | R11: =IF(F11<13,"Young (<13 mo)","Mature (13+ mo)") -> Mature (13+ mo) | S11: Revenue implies ~$312/unit; not used
A12: =Raw_Data!A12 -> ST-111 | B12: =Raw_Data!B12 -> Midwest | C12: =IF(B12="Pacific NW","Pacific Northwest",B12) -> Midwest | D12: =Raw_Data!C12 -> Full-line | E12: =IF(Raw_Data!D12="","",Raw_Data!D12) -> 27096 | F12: =Raw_Data!E12 -> 143 | G12: =Raw_Data!F12 -> 493 | H12: =Raw_Data!G12 -> 2090 | I12: =Raw_Data!H12 -> 75305 | J12: =Raw_Data!I12 -> 4.2 | K12: =Raw_Data!J12 -> 2.3 | L12: =Raw_Data!K12 -> 8.1 | M12: =Raw_Data!L12 -> 4.7 | N12: =H12/G12 -> 4.2393509 | O12: =I12/G12 -> 152.74848 | P12: =I12/H12 -> 36.0311 | Q12: =J12-N12 -> -0.039350913 | R12: =IF(F12<13,"Young (<13 mo)","Mature (13+ mo)") -> Mature (13+ mo)
A13: =Raw_Data!A13 -> ST-112 | B13: =Raw_Data!B13 -> Midwest | C13: =IF(B13="Pacific NW","Pacific Northwest",B13) -> Midwest | D13: =Raw_Data!C13 -> Compact | E13: =IF(Raw_Data!D13="","",Raw_Data!D13) -> 10196 | F13: =Raw_Data!E13 -> 102 | G13: =Raw_Data!F13 -> 185 | H13: =Raw_Data!G13 -> 677 | I13: =Raw_Data!H13 -> 20522 | J13: =Raw_Data!I13 -> 3.7 | K13: =Raw_Data!J13 -> 3 | L13: =Raw_Data!K13 -> 3.7 | M13: =Raw_Data!L13 -> 6.1 | N13: =H13/G13 -> 3.6594595 | O13: =I13/G13 -> 110.92973 | P13: =I13/H13 -> 30.313146 | Q13: =J13-N13 -> 0.040540541 | R13: =IF(F13<13,"Young (<13 mo)","Mature (13+ mo)") -> Mature (13+ mo)
A14: =Raw_Data!A15 -> ST-113 | B14: =Raw_Data!B15 -> Midwest | C14: =IF(B14="Pacific NW","Pacific Northwest",B14) -> Midwest | D14: =Raw_Data!C15 -> Outlet | E14: =IF(Raw_Data!D15="","",Raw_Data!D15) -> 21882 | F14: =Raw_Data!E15 -> 66 | G14: =Raw_Data!F15 -> 398 | H14: =Raw_Data!G15 -> 2022 | I14: =Raw_Data!H15 -> 40482 | J14: =Raw_Data!I15 -> 5.1 | K14: =Raw_Data!J15 -> 3.8 | L14: =Raw_Data!K15 -> 5.6 | M14: =Raw_Data!L15 -> 8.2 | N14: =H14/G14 -> 5.080402 | O14: =I14/G14 -> 101.71357 | P14: =I14/H14 -> 20.020772 | Q14: =J14-N14 -> 0.01959799 | R14: =IF(F14<13,"Young (<13 mo)","Mature (13+ mo)") -> Mature (13+ mo)
A15: =Raw_Data!A16 -> ST-114 | B15: =Raw_Data!B16 -> Midwest | C15: =IF(B15="Pacific NW","Pacific Northwest",B15) -> Midwest | D15: =Raw_Data!C16 -> Full-line | E15: =IF(Raw_Data!D16="","",Raw_Data!D16) -> 26981 | F15: =Raw_Data!E16 -> 3 | G15: =Raw_Data!F16 -> 491 | H15: =Raw_Data!G16 -> 2018 | I15: =Raw_Data!H16 -> 70209 | J15: =Raw_Data!I16 -> 4.1 | K15: =Raw_Data!J16 -> 3.1 | L15: =Raw_Data!K16 -> 5.3 | M15: =Raw_Data!L16 -> 8.7 | N15: =H15/G15 -> 4.1099796 | O15: =I15/G15 -> 142.99185 | P15: =I15/H15 -> 34.791378 | Q15: =J15-N15 -> -0.0099796334 | R15: =IF(F15<13,"Young (<13 mo)","Mature (13+ mo)") -> Young (<13 mo) | S15: 3 months open; AI "vs same quarter last year" unsupported
A16: =Raw_Data!A17 -> ST-115 | B16: =Raw_Data!B17 -> Northeast | C16: =IF(B16="Pacific NW","Pacific Northwest",B16) -> Northeast | D16: =Raw_Data!C17 -> Full-line | E16: =IF(Raw_Data!D17="","",Raw_Data!D17) -> 32602 | F16: =Raw_Data!E17 -> 156 | G16: =Raw_Data!F17 -> 593 | H16: =Raw_Data!G17 -> 2384 | I16: =Raw_Data!H17 -> 81269 | J16: =Raw_Data!I17 -> 4 | K16: =Raw_Data!J17 -> 8.1 | L16: =Raw_Data!K17 -> 7.3 | M16: =Raw_Data!L17 -> 7.9 | N16: =H16/G16 -> 4.0202361 | O16: =I16/G16 -> 137.04722 | P16: =I16/H16 -> 34.089346 | Q16: =J16-N16 -> -0.020236088 | R16: =IF(F16<13,"Young (<13 mo)","Mature (13+ mo)") -> Mature (13+ mo)
A17: =Raw_Data!A18 -> ST-116 | B17: =Raw_Data!B18 -> Northeast | C17: =IF(B17="Pacific NW","Pacific Northwest",B17) -> Northeast | D17: =Raw_Data!C18 -> Compact | E17: =IF(Raw_Data!D18="","",Raw_Data!D18) -> 9615 | F17: =Raw_Data!E18 -> 84 | G17: =Raw_Data!F18 -> 175 | H17: =Raw_Data!G18 -> 656 | I17: =Raw_Data!H18 -> 18057 | J17: =Raw_Data!I18 -> 3.8 | K17: =Raw_Data!J18 -> 4.9 | L17: =Raw_Data!K18 -> 3.4 | M17: =Raw_Data!L18 -> 5 | N17: =H17/G17 -> 3.7485714 | O17: =I17/G17 -> 103.18286 | P17: =I17/H17 -> 27.525915 | Q17: =J17-N17 -> 0.051428571 | R17: =IF(F17<13,"Young (<13 mo)","Mature (13+ mo)") -> Mature (13+ mo)
A18: =Raw_Data!A19 -> ST-117 | B18: =Raw_Data!B19 -> Northeast | C18: =IF(B18="Pacific NW","Pacific Northwest",B18) -> Northeast | D18: =Raw_Data!C19 -> Outlet | E18: =IF(Raw_Data!D19="","",Raw_Data!D19) -> 20389 | F18: =Raw_Data!E19 -> 71 | G18: =Raw_Data!F19 -> 371 | H18: =Raw_Data!G19 -> 1881 | I18: =Raw_Data!H19 -> 41627 | J18: =Raw_Data!I19 -> 5.1 | K18: =Raw_Data!J19 -> 1.3 | L18: =Raw_Data!K19 -> 6.2 | M18: =Raw_Data!L19 -> 11.4 | N18: =H18/G18 -> 5.0700809 | O18: =I18/G18 -> 112.20216 | P18: =I18/H18 -> 22.13025 | Q18: =J18-N18 -> 0.029919137 | R18: =IF(F18<13,"Young (<13 mo)","Mature (13+ mo)") -> Mature (13+ mo) | S18: Error rose 6.2 to 11.4; AI says improved
A19: =Raw_Data!A20 -> ST-118 | B19: =Raw_Data!B20 -> Northeast | C19: =IF(B19="Pacific NW","Pacific Northwest",B19) -> Northeast | D19: =Raw_Data!C20 -> Compact | E19: =IF(Raw_Data!D20="","",Raw_Data!D20) -> 9526 | F19: =Raw_Data!E20 -> 47 | G19: =Raw_Data!F20 -> 173 | H19: =Raw_Data!G20 -> 661 | I19: =Raw_Data!H20 -> 18254 | J19: =Raw_Data!I20 -> 3.8 | K19: =Raw_Data!J20 -> 8.1 | L19: =Raw_Data!K20 -> 5.3 | M19: =Raw_Data!L20 -> 3.9 | N19: =H19/G19 -> 3.8208092 | O19: =I19/G19 -> 105.51445 | P19: =I19/H19 -> 27.615734 | Q19: =J19-N19 -> -0.020809249 | R19: =IF(F19<13,"Young (<13 mo)","Mature (13+ mo)") -> Mature (13+ mo)
A20: =Raw_Data!A21 -> ST-119 | B20: =Raw_Data!B21 -> Southeast | C20: =IF(B20="Pacific NW","Pacific Northwest",B20) -> Southeast | D20: =Raw_Data!C21 -> Full-line | E20: =IF(Raw_Data!D21="","",Raw_Data!D21) -> 25116 | F20: =Raw_Data!E21 -> 91 | G20: =Raw_Data!F21 -> 457 | H20: =Raw_Data!G21 -> 1842 | I20: =Raw_Data!H21 -> 63338 | J20: =Raw_Data!I21 -> 4 | K20: =Raw_Data!J21 -> 8.4 | L20: =Raw_Data!K21 -> 4.8 | M20: =Raw_Data!L21 -> 5.9 | N20: =H20/G20 -> 4.0306346 | O20: =I20/G20 -> 138.59519 | P20: =I20/H20 -> 34.385451 | Q20: =J20-N20 -> -0.030634573 | R20: =IF(F20<13,"Young (<13 mo)","Mature (13+ mo)") -> Mature (13+ mo)
A21: =Raw_Data!A22 -> ST-120 | B21: =Raw_Data!B22 -> Southeast | C21: =IF(B21="Pacific NW","Pacific Northwest",B21) -> Southeast | D21: =Raw_Data!C22 -> Compact | E21: =IF(Raw_Data!D22="","",Raw_Data!D22) | F21: =Raw_Data!E22 -> 55 | G21: =Raw_Data!F22 -> 234 | H21: =Raw_Data!G22 -> 842 | I21: =Raw_Data!H22 -> 23885 | J21: =Raw_Data!I22 -> 3.6 | K21: =Raw_Data!J22 -> 6.9 | L21: =Raw_Data!K22 -> 4.2 | M21: =Raw_Data!L22 -> 9.8 | N21: =H21/G21 -> 3.5982906 | O21: =I21/G21 -> 102.07265 | P21: =I21/H21 -> 28.366983 | Q21: =J21-N21 -> 0.0017094017 | R21: =IF(F21<13,"Young (<13 mo)","Mature (13+ mo)") -> Mature (13+ mo) | S21: Square footage blank; not used
A22: =Raw_Data!A23 -> ST-121 | B22: =Raw_Data!B23 -> Southeast | C22: =IF(B22="Pacific NW","Pacific Northwest",B22) -> Southeast | D22: =Raw_Data!C23 -> Outlet | E22: =IF(Raw_Data!D23="","",Raw_Data!D23) -> 19981 | F22: =Raw_Data!E23 -> 39 | G22: =Raw_Data!F23 -> 363 | H22: =Raw_Data!G23 -> 1931 | I22: =Raw_Data!H23 -> 38277 | J22: =Raw_Data!I23 -> 5.3 | K22: =Raw_Data!J23 -> 1.6 | L22: =Raw_Data!K23 -> 6.7 | M22: =Raw_Data!L23 -> 9.9 | N22: =H22/G22 -> 5.3195592 | O22: =I22/G22 -> 105.44628 | P22: =I22/H22 -> 19.822372 | Q22: =J22-N22 -> -0.019559229 | R22: =IF(F22<13,"Young (<13 mo)","Mature (13+ mo)") -> Mature (13+ mo)
A23: =Raw_Data!A24 -> ST-122 | B23: =Raw_Data!B24 -> Southeast | C23: =IF(B23="Pacific NW","Pacific Northwest",B23) -> Southeast | D23: =Raw_Data!C24 -> Full-line | E23: =IF(Raw_Data!D24="","",Raw_Data!D24) -> 33561 | F23: =Raw_Data!E24 -> 128 | G23: =Raw_Data!F24 -> 610 | H23: =Raw_Data!G24 -> 2568 | I23: =Raw_Data!H24 -> 88236 | J23: =Raw_Data!I24 -> 4.2 | K23: =Raw_Data!J24 -> 104 | L23: =Raw_Data!K24 -> 5.8 | M23: =Raw_Data!L24 -> 4.7 | N23: =H23/G23 -> 4.2098361 | O23: =I23/G23 -> 144.64918 | P23: =I23/H23 -> 34.359813 | Q23: =J23-N23 -> -0.0098360656 | R23: =IF(F23<13,"Young (<13 mo)","Mature (13+ mo)") -> Mature (13+ mo) | S23: Stockout 104% impossible; not used
A25: 22 unique stores. Yellow = row with a data issue (see data_note). Values link to Raw_Data; nothing overwritten.

Sheet Chart_Data
A1: Chart data (every chart reads from here)
A2: Values are looked up from Clean_Data by store_id. Blue = typed input. Row order is fixed (see README).
A3: V1 store_id | B3: V1 reported units/labor hr | D3: V2 store_id | E3: V2 recalculated units/labor hr | F3: Region | H3: V3 cohort | I3: V3 store_id | J3: Months open | K3: Recalculated units/labor hr | M3: Threshold x (months) | N3: Threshold y | P3: Band low x | Q3: Band low y (min of mature) | S3: Band high x | T3: Band high y (max of mature)
A4: ST-102 | B4: =INDEX(Clean_Data!$J$2:$J$23,MATCH(A4,Clean_Data!$A$2:$A$23,0)) -> 3.4 | D4: ST-104 | E4: =INDEX(Clean_Data!$N$2:$N$23,MATCH(D4,Clean_Data!$A$2:$A$23,0)) -> 2.4398148 | F4: =INDEX(Clean_Data!$C$2:$C$23,MATCH(D4,Clean_Data!$A$2:$A$23,0)) -> Mountain | H4: Young Mountain Compact | I4: ST-104 | J4: =INDEX(Clean_Data!$F$2:$F$23,MATCH(I4,Clean_Data!$A$2:$A$23,0)) -> 4 | K4: =INDEX(Clean_Data!$N$2:$N$23,MATCH(I4,Clean_Data!$A$2:$A$23,0)) -> 2.4398148 | M4: 13 | N4: 0 | P4: 0 | Q4: =MIN($K$7:$K$12) -> 3.3891403 | S4: 0 | T4: =MAX($K$7:$K$12) -> 3.8208092
A5: ST-104 | B5: =INDEX(Clean_Data!$J$2:$J$23,MATCH(A5,Clean_Data!$A$2:$A$23,0)) -> 2.4 | D5: ST-105 | E5: =INDEX(Clean_Data!$N$2:$N$23,MATCH(D5,Clean_Data!$A$2:$A$23,0)) -> 2.9787234 | F5: =INDEX(Clean_Data!$C$2:$C$23,MATCH(D5,Clean_Data!$A$2:$A$23,0)) -> Mountain | H5: Young Mountain Compact | I5: ST-105 | J5: =INDEX(Clean_Data!$F$2:$F$23,MATCH(I5,Clean_Data!$A$2:$A$23,0)) -> 7 | K5: =INDEX(Clean_Data!$N$2:$N$23,MATCH(I5,Clean_Data!$A$2:$A$23,0)) -> 2.9787234 | M5: 13 | N5: 4.5 | P5: 150 | Q5: =MIN($K$7:$K$12) -> 3.3891403 | S5: 150 | T5: =MAX($K$7:$K$12) -> 3.8208092
A6: ST-105 | B6: =INDEX(Clean_Data!$J$2:$J$23,MATCH(A6,Clean_Data!$A$2:$A$23,0)) -> 3 | D6: ST-106 | E6: =INDEX(Clean_Data!$N$2:$N$23,MATCH(D6,Clean_Data!$A$2:$A$23,0)) -> 3.0782609 | F6: =INDEX(Clean_Data!$C$2:$C$23,MATCH(D6,Clean_Data!$A$2:$A$23,0)) -> Mountain | H6: Young Mountain Compact | I6: ST-106 | J6: =INDEX(Clean_Data!$F$2:$F$23,MATCH(I6,Clean_Data!$A$2:$A$23,0)) -> 9 | K6: =INDEX(Clean_Data!$N$2:$N$23,MATCH(I6,Clean_Data!$A$2:$A$23,0)) -> 3.0782609
A7: ST-106 | B7: =INDEX(Clean_Data!$J$2:$J$23,MATCH(A7,Clean_Data!$A$2:$A$23,0)) -> 6.8 | D7: ST-102 | E7: =INDEX(Clean_Data!$N$2:$N$23,MATCH(D7,Clean_Data!$A$2:$A$23,0)) -> 3.3891403 | F7: =INDEX(Clean_Data!$C$2:$C$23,MATCH(D7,Clean_Data!$A$2:$A$23,0)) -> Pacific Northwest | H7: Mature Compact | I7: ST-118 | J7: =INDEX(Clean_Data!$F$2:$F$23,MATCH(I7,Clean_Data!$A$2:$A$23,0)) -> 47 | K7: =INDEX(Clean_Data!$N$2:$N$23,MATCH(I7,Clean_Data!$A$2:$A$23,0)) -> 3.8208092 | M7: Threshold = comparable-store definition (open 13+ months), AI300 glossary.
A8: ST-109 | B8: =INDEX(Clean_Data!$J$2:$J$23,MATCH(A8,Clean_Data!$A$2:$A$23,0)) -> 3.6 | D8: ST-120 | E8: =INDEX(Clean_Data!$N$2:$N$23,MATCH(D8,Clean_Data!$A$2:$A$23,0)) -> 3.5982906 | F8: =INDEX(Clean_Data!$C$2:$C$23,MATCH(D8,Clean_Data!$A$2:$A$23,0)) -> Southeast | H8: Mature Compact | I8: ST-120 | J8: =INDEX(Clean_Data!$F$2:$F$23,MATCH(I8,Clean_Data!$A$2:$A$23,0)) -> 55 | K8: =INDEX(Clean_Data!$N$2:$N$23,MATCH(I8,Clean_Data!$A$2:$A$23,0)) -> 3.5982906
A9: ST-112 | B9: =INDEX(Clean_Data!$J$2:$J$23,MATCH(A9,Clean_Data!$A$2:$A$23,0)) -> 3.7 | D9: ST-109 | E9: =INDEX(Clean_Data!$N$2:$N$23,MATCH(D9,Clean_Data!$A$2:$A$23,0)) -> 3.6080402 | F9: =INDEX(Clean_Data!$C$2:$C$23,MATCH(D9,Clean_Data!$A$2:$A$23,0)) -> Southwest | H9: Mature Compact | I9: ST-109 | J9: =INDEX(Clean_Data!$F$2:$F$23,MATCH(I9,Clean_Data!$A$2:$A$23,0)) -> 68 | K9: =INDEX(Clean_Data!$N$2:$N$23,MATCH(I9,Clean_Data!$A$2:$A$23,0)) -> 3.6080402
A10: ST-116 | B10: =INDEX(Clean_Data!$J$2:$J$23,MATCH(A10,Clean_Data!$A$2:$A$23,0)) -> 3.8 | D10: ST-112 | E10: =INDEX(Clean_Data!$N$2:$N$23,MATCH(D10,Clean_Data!$A$2:$A$23,0)) -> 3.6594595 | F10: =INDEX(Clean_Data!$C$2:$C$23,MATCH(D10,Clean_Data!$A$2:$A$23,0)) -> Midwest | H10: Mature Compact | I10: ST-116 | J10: =INDEX(Clean_Data!$F$2:$F$23,MATCH(I10,Clean_Data!$A$2:$A$23,0)) -> 84 | K10: =INDEX(Clean_Data!$N$2:$N$23,MATCH(I10,Clean_Data!$A$2:$A$23,0)) -> 3.7485714
A11: ST-118 | B11: =INDEX(Clean_Data!$J$2:$J$23,MATCH(A11,Clean_Data!$A$2:$A$23,0)) -> 3.8 | D11: ST-116 | E11: =INDEX(Clean_Data!$N$2:$N$23,MATCH(D11,Clean_Data!$A$2:$A$23,0)) -> 3.7485714 | F11: =INDEX(Clean_Data!$C$2:$C$23,MATCH(D11,Clean_Data!$A$2:$A$23,0)) -> Northeast | H11: Mature Compact | I11: ST-112 | J11: =INDEX(Clean_Data!$F$2:$F$23,MATCH(I11,Clean_Data!$A$2:$A$23,0)) -> 102 | K11: =INDEX(Clean_Data!$N$2:$N$23,MATCH(I11,Clean_Data!$A$2:$A$23,0)) -> 3.6594595
A12: ST-120 | B12: =INDEX(Clean_Data!$J$2:$J$23,MATCH(A12,Clean_Data!$A$2:$A$23,0)) -> 3.6 | D12: ST-118 | E12: =INDEX(Clean_Data!$N$2:$N$23,MATCH(D12,Clean_Data!$A$2:$A$23,0)) -> 3.8208092 | F12: =INDEX(Clean_Data!$C$2:$C$23,MATCH(D12,Clean_Data!$A$2:$A$23,0)) -> Northeast | H12: Mature Compact | I12: ST-102 | J12: =INDEX(Clean_Data!$F$2:$F$23,MATCH(I12,Clean_Data!$A$2:$A$23,0)) -> 130 | K12: =INDEX(Clean_Data!$N$2:$N$23,MATCH(I12,Clean_Data!$A$2:$A$23,0)) -> 3.3891403

Sheet Summary
A1: Summary statistics and reconciliations
A3: Measure | B3: Value | C3: Note / source
A4: Rows in raw file | B4: =COUNTA(Raw_Data!A2:A24) -> 23 | C4: Raw_Data
A5: Unique stores after removing duplicate | B5: =COUNTA(Clean_Data!A2:A23) -> 22 | C5: ST-112 repeated
A6: Compact stores | B6: =COUNTIF(Clean_Data!D2:D23,"Compact") -> 9
A7: Units per week, de-duplicated | B7: =SUM(Clean_Data!H2:H23) -> 32904 | C7: Compare to merchandising report below
A8: Units per week per merchandising report | B8: 32904 | C8: Reference Section 4, Extract Facts (input)
A9: Units difference | B9: =B7-B8 -> 0 | C9: 0 = reconciles
A10: Scheduled hours, all 23 raw rows | B10: =SUM(Raw_Data!F2:F24) -> 8015 | C10: Raw_Data
A11: Scheduled hours per Extract Facts | B11: 8015 | C11: Reference Section 4 (input)
A12: Scheduled hours, de-duplicated | B12: =SUM(Clean_Data!G2:G23) -> 7830
A13: Hours difference: stated minus de-duplicated | B13: =B11-B12 -> 185 | C13: 185 = ST-112 hours; stated figure includes the duplicate
A14: Mature Compact mean units/labor hr (n=6) | B14: =AVERAGEIFS(Clean_Data!N2:N23,Clean_Data!D2:D23,"Compact",Clean_Data!F2:F23,">=13") -> 3.6373852 | C14: Unweighted mean of store values
A15: Young Mountain Compact mean units/labor hr (n=3) | B15: =AVERAGEIFS(Clean_Data!N2:N23,Clean_Data!D2:D23,"Compact",Clean_Data!F2:F23,"<13") -> 2.8322664
A16: Gap, young vs mature | B16: =1-B15/B14 -> 0.2213455
A17: Mature Compact minimum | B17: =MIN(Chart_Data!K7:K12) -> 3.3891403
A18: Mature Compact maximum | B18: =MAX(Chart_Data!K7:K12) -> 3.8208092
A19: Mature Compact mean revenue per labor hour ($) | B19: =AVERAGEIFS(Clean_Data!O2:O23,Clean_Data!D2:D23,"Compact",Clean_Data!F2:F23,">=13") -> 103.58371 | C19: Cross-check measure
A20: Young Mountain Compact mean revenue per labor hour ($) | B20: =AVERAGEIFS(Clean_Data!O2:O23,Clean_Data!D2:D23,"Compact",Clean_Data!F2:F23,"<13") -> 81.176229
A21: Chain mean units/labor hr, recalculated (unweighted) | B21: =AVERAGE(Clean_Data!N2:N23) -> 4.0705392
A22: Chain mean units/labor hr, reported column (unweighted) | B22: =AVERAGE(Clean_Data!J2:J23) -> 4.2409091 | C22: Inflated by ST-106 stale 6.8
A23: ST-110 implied revenue per unit ($) | B23: =INDEX(Clean_Data!P2:P23,MATCH("ST-110",Clean_Data!A2:A23,0)) -> 312 | C23: Implausible
A24: Other stores: minimum revenue per unit ($) | B24: =MIN(Clean_Data!P2:P10,Clean_Data!P12:P23) -> 19.822372 | C24: Excludes ST-110 (row 11 of Clean_Data)
A25: Other stores: maximum revenue per unit ($) | B25: =MAX(Clean_Data!P2:P10,Clean_Data!P12:P23) -> 36.0311
A26: Full-line Mountain store ST-107 units/labor hr | B26: =INDEX(Clean_Data!N2:N23,MATCH("ST-107",Clean_Data!A2:A23,0)) -> 4.2991453 | C26: Region alone does not explain the gap
A27: Young Full-line ST-114 units/labor hr | B27: =INDEX(Clean_Data!N2:N23,MATCH("ST-114",Clean_Data!A2:A23,0)) -> 4.1099796 | C27: Newness alone does not show a gap

Sheet Charts
A1: Charts (native Excel charts; edit the data on Chart_Data)
A2: Fictional classroom example. Q1 2026 store-level averages over 13 weeks (not a time series). 9 Compact stores; duplicate ST-112 row removed. Source: BrightPath_Store_Performance_Sample.csv.
A4: V1: initial version (flawed on purpose: reported column, alphabetical, no axis title)
A26: V2: first revision (recalculated, sorted, Mountain highlighted)
A48: V3: final version (months open vs productivity)
