Workbook

Sheet Boeing Stock Price History (1)
A1: Date | B1: Price | C1: Open | D1: High | E1: Low | F1: Vol.
A2: 46131 | B2: 225.11 | C2: 222.33 | D2: 225.32 | E2: 220.37 | F2: 4.63M
A3: 46124 | B3: 223.38 | C3: 216.25 | D3: 230.24 | E3: 215.4 | F3: 29.32M
A4: 46117 | B4: 217.63 | C4: 207.37 | D4: 221.29 | E4: 206.92 | F4: 24.12M
A5: 46110 | B5: 208.22 | C5: 191.48 | D5: 210.28 | E5: 187.72 | F5: 32.64M
A6: 46103 | B6: 190.52 | C6: 198.91 | D6: 201.69 | E6: 189.28 | F6: 28.77M
A7: 46096 | B7: 195.12 | C7: 210.75 | D7: 217.15 | E7: 192.54 | F7: 43.43M
A8: 46089 | B8: 209.89 | C8: 226.75 | D8: 227.59 | E8: 204.3 | F8: 45.31M
A9: 46082 | B9: 231.11 | C9: 226 | D9: 231.96 | E9: 218.13 | F9: 33.87M
A10: 46075 | B10: 227.53 | C10: 231.5 | D10: 236.13 | E10: 224.91 | F10: 25.12M
A11: 46068 | B11: 232.03 | C11: 243.61 | D11: 245.42 | E11: 231.14 | F11: 21.08M
A12: 46061 | B12: 242.96 | C12: 242 | D12: 247.86 | E12: 235.5 | F12: 29.50M
A13: 46054 | B13: 243.03 | C13: 232.64 | D13: 246.3 | E13: 228.96 | F13: 34.89M
... A314: 43947 | B314: 133.37 | C314: 129.97 | D314: 147.18 | E314: 123.83 | F314: 207.31M

Sheet WACC
A1: Assumption | B1: Value | C1: Source
A2: Risk-Free Rate (Rf) | B2: 0.04258 | C2: US 10-Year Treasury Yield
A3: Market Risk Premium (Rm - Rf) | B3: 0.055 | C3: Academic Standard (Damodaran/Ibbotson)
A4: Boeing 5-Year Beta (β) | B4: 1.13 | C4: Yahoo Finance Summary Statistics
A5: Pre-Tax Cost of Debt (Rd) | B5: 0.052 | C5: Boeing 2025 10-K, Note 17 (estimated avg. yield)
A6: Corporate Tax Rate (Tc) | B6: 0.21 | C6: U.S. Federal Statutory Rate (10-K, Note 6)
A7: Market Value of Equity (E) | B7: 170370000000 | C7: Yahoo Finance (Market Cap in $)
A8: Market Value of Debt (D) | B8: 54100000000 | C8: Boeing 2025 10-K, Item 7 (Liquidity section)
A10: Cost of Equity – CAPM
A11: CAPM Formula
A15: Component | B15: Value
A16: Risk-Free Rate (Rf) | B16: =B2 -> 0.04258
A17: Beta (β) | B17: =B4 -> 1.13
A18: Market Risk Premium | B18: =B3 -> 0.055
A19: Cost of Equity (CAPM) | B19: =B16+(B17*B18) -> 0.10473
A22: Cost of Debt
A23: Pre-Tax Cost of Debt | B23: =B5 -> 0.052
A24: Tax Rate | B24: =B6 -> 0.21
A25: After-Tax Cost of Debt | B25: =B2*(1-B3) -> 0.0402381
A27: Capital Structure Weights
A28: Component | B28: Value
A29: Market Value of Equity (E) | B29: =B7 -> 170370000000
A30: Market Value of Debt (D) | B30: =B8 -> 54100000000
A31: Total Market Value (V) | B31: =SUM(B29:B30) -> 224470000000
A32: Equity Weight (E/V) | B32: =B29/B31 -> 0.75898784
A33: Debt Weight (D/V) | B33: =B30/B31 -> 0.24101216
A39: WACC Calculation
A40: Component | B40: Value
A41: Cost of Equity (Re) | B41: =B19 -> 0.10473
A42: Equity Weight (E/V) | B42: =B32 -> 0.75898784
A43: Equity Component | B43: =B41*B42 -> 0.079488796
A44: After-Tax Cost of Debt | B44: =B25 -> 0.0402381
A45: Debt Weight (D/V) | B45: =B33 -> 0.24101216
A46: Debt Component | B46: =B44*B45 -> 0.0096978715
A47: WACC | B47: =B46+B43 -> 0.089186668

Sheet Project Cash Flow
A1: Assumption | B1: Value | C1: Notes | J1: Component | K1: Value
A2: Initial Investment (Year 0) | B2: 5000000 | C2: Given in project outline | J2: Initial Investment | K2: =B2 -> 5000000
A3: Salvage Value (Year 5) | B3: 1000000 | C3: Given in project outline | J3: Salvage Value | K3: =B3 -> 1000000
A4: Project Life (Years) | B4: 5 | C4: Given in project outline | J4: Depreciable Base | K4: =B2-B3 -> 4000000
A5: Tax Rate (Tc) | B5: =WACC!B6 -> 0.21 | C5: Reference from WACC Inputs tab | J5: Project Life (Years) | K5: =B4 -> 5
A6: Operating Cost (% of Revenue) | B6: 0.6 | C6: Given as 60% of annual revenues | J6: Annual Depreciation | K6: =K4/K5 -> 800000
B8: Year 0 | C8: Year 1 | D8: Year 2 | E8: Year 3 | F8: Year 4 | G8: Year 5
A9: Revenue | C9: 2000000 | D9: 4000000 | E9: 5000000 | F9: 5500000 | G9: 6000000
A10: Less: Depreciation | C10: =$K$6 -> 800000 | D10: =$K$6 -> 800000 | E10: =$K$6 -> 800000 | F10: =$K$6 -> 800000 | G10: =$K$6 -> 800000
A11: Less: Operating Costs | C11: =$B$6*C9 -> 1200000 | D11: =$B$6*D9 -> 2400000 | E11: =$B$6*E9 -> 3000000 | F11: =$B$6*F9 -> 3300000 | G11: =$B$6*G9 -> 3600000
A12: EBIT | C12: =C9-C10-C11 -> 0 | D12: =D9-D10-D11 -> 800000 | E12: =E9-E10-E11 -> 1200000 | F12: =F9-F10-F11 -> 1400000 | G12: =G9-G10-G11 -> 1600000
A13: Less: Tax | C13: =$B$5*C12 -> 0 | D13: =$B$5*D12 -> 168000 | E13: =$B$5*E12 -> 252000 | F13: =$B$5*F12 -> 294000 | G13: =$B$5*G12 -> 336000
A14: NOPAT | C14: =C12-C13 -> 0 | D14: =D12-D13 -> 632000 | E14: =E12-E13 -> 948000 | F14: =F12-F13 -> 1106000 | G14: =G12-G13 -> 1264000
A15: Add: Depreciation | C15: =$K$6 -> 800000 | D15: =$K$6 -> 800000 | E15: =$K$6 -> 800000 | F15: =$K$6 -> 800000 | G15: =$K$6 -> 800000
A16: Operating Cash Flow | C16: =C15+C14 -> 800000 | D16: =D15+D14 -> 1432000 | E16: =E15+E14 -> 1748000 | F16: =F15+F14 -> 1906000 | G16: =G15+G14 -> 2064000
A17: Initial Investment | B17: =(B2) -> 5000000
A18: After-Tax Salvage Value | G18: =B3 -> 1000000
A19: Free Cash Flow | B19: =B17 -> 5000000 | C19: =C16 -> 800000 | D19: =D16 -> 1432000 | E19: =E16 -> 1748000 | F19: =F16 -> 1906000 | G19: =G16+G18 -> 3064000

Sheet Financial Analysis
B1: 0 | C1: 1 | D1: 2 | E1: 3 | F1: 4 | G1: 5
A2: WACC | B2: =WACC!B47 -> 0.089186668
A3: Free Cash Flow | B3: =-'Project Cash Flow'!B19 -> -5000000 | C3: ='Project Cash Flow'!C19 -> 800000 | D3: ='Project Cash Flow'!D19 -> 1432000 | E3: ='Project Cash Flow'!E19 -> 1748000 | F3: ='Project Cash Flow'!F19 -> 1906000 | G3: ='Project Cash Flow'!G19 -> 3064000
B4: =B3 -> -5000000 | C4: =C3/(1+$B$2)^C1 -> 734493.02 | D4: =D3/(1+$B$2)^D1 -> 1207086.5 | E4: =E3/(1+$B$2)^E1 -> 1352802.8 | F4: =F3/(1+$B$2)^F1 -> 1354296.1 | G4: =G3/(1+$B$2)^G1 -> 1998836.1
A6: Base NPV | B6: =NPV(B2, C3:G3) -> 6647514.4
A7: Initial Investment | B7: =B3 -> -5000000
A8: NPV | B8: =SUM(B6:B7) -> 1647514.4
A10: IRR | B10: =IRR(B3:G3) -> 0.18669745
A12: Payback Period
B13: 0 | C13: 1 | D13: 2 | E13: 3 | F13: 4 | G13: 5
B14: =B3 -> -5000000 | C14: =B14+C3 -> -4200000 | D14: =C14+D3 -> -2768000 | E14: =D14+E3 -> -1020000 | F14: =E14+F3 -> 886000 | G14: =F14+G3 -> 3950000
A16: Y3 Cummulative Balance | B16: =ABS(E14) -> 1020000
A17: Cash Flow Year 3 | B17: =F3 -> 1906000
A18: Fraction of Year 4 | B18: =B16/B17 -> 0.53515215
A19: Payback Period | B19: =3+B18 -> 3.5351522
A22: Sensitivity Analysis
A23: A) Impact of WACC on NPV
A24: Value | B24: NPV
A25: 0.07 | B25: =B8 -> 1647514.4
A26: 0.075 | B26: 1951882.9
A27: 0.08 | B27: 1842342.5
A28: 0.085 | B28: 1735290.3
A29: 0.0892 | B29: 1647237.6
A30: 0.095 | B30: 1528370.4
A31: 0.1 | B31: 1428368.7
A32: 0.105 | B32: 1330586.6
A33: 0.11 | B33: 1234962.7
A34: B) Impact of Revenue Decline on NPV and IRR
A35: Assumption | B35: =100% -> 1 | C35: ='Project Cash Flow'!C9*'Financial Analysis'!$B$35 -> 2000000 | D35: ='Project Cash Flow'!D9*'Financial Analysis'!$B$35 -> 4000000 | E35: ='Project Cash Flow'!E9*'Financial Analysis'!$B$35 -> 5000000 | F35: ='Project Cash Flow'!F9*'Financial Analysis'!$B$35 -> 5500000 | G35: ='Project Cash Flow'!G9*'Financial Analysis'!$B$35 -> 6000000
A36: Value | B36: NPV | C36: IRR
A37: =100% -> 1 | B37: =B8 -> 1647514.4 | C37: =B10 -> 0.18669745
A38: =90% -> 0.9 | B38: 1647514.4 | C38: 0.18669745
A39: =80% -> 0.8 | B39: 1647514.4 | C39: 0.18669745
A40: =70% -> 0.7 | B40: 1647514.4 | C40: 0.18669745
A41: 0.6 | B41: 1647514.4 | C41: 0.18669745
A42: 0.5 | B42: 1647514.4 | C42: 0.18669745
A43: 0.4 | B43: 1647514.4 | C43: 0.18669745
