Workbook

Sheet Sales Budget
B2: January | C2: February | D2: March | E2: Q1
A3: Budgeted Sales in Units | B3: 30000 | C3: 40000 | D3: 50000 | E3: =SUM(B3:D3) -> 120000
A4: Selling Price per Unit | B4: 60 | C4: =B4 -> 60 | D4: =B4 -> 60 | E4: =B4 -> 60
A5: Total Budgeted Sales | B5: =B3*B4 -> 1800000 | C5: =C3*C4 -> 2400000 | D5: =D3*D4 -> 3000000 | E5: =E3*E4 -> 7200000

Sheet Cash Collections
B2: January | C2: February | D2: March | E2: Q1
A3: AR Balance $1,770,000 | B3: =1500000*0.2+2100000*0.5 -> 1350000 | C3: =2100000*0.2 -> 420000 | D3: 0 | F3: Remember to spread the AR balance according to collection pattern
A4: Jan Sales
A5: 0.3 | B5: ='Sales Budget'!$B$5*A5 -> 540000
A6: 0.5 | C6: ='Sales Budget'!$B$5*A6 -> 900000
A7: 0.2 | D7: ='Sales Budget'!$B$5*A7 -> 360000
A8: Feb Sales
A9: 0.3 | C9: ='Sales Budget'!$C$5*A9 -> 720000
A10: 0.5 | D10: ='Sales Budget'!$C$5*A10 -> 1200000
A11: 0.2
A12: March Sales
A13: 0.3 | D13: ='Sales Budget'!$D$5*A13 -> 900000
A14: 0.5
A15: 0.2
A16: Totals | B16: =SUM(B3:B15) -> 1890000 | C16: =SUM(C3:C15) -> 2040000 | D16: =SUM(D3:D15) -> 2460000 | E16: =SUM(B16:D16) -> 6390000
A18: AR at end of Q1 | B18: ='Sales Budget'!C5*A11+'Sales Budget'!D5*(A14+A15) -> 2580000 | F18: This will be used in your ending balance sheet

Sheet Production
B2: January | C2: February | D2: March | E2: Q1 | F2: April | G2: May
A3: Budgeted Sales in Units | B3: ='Sales Budget'!B3 -> 30000 | C3: ='Sales Budget'!C3 -> 40000 | D3: ='Sales Budget'!D3 -> 50000 | E3: =SUM(B3:D3) -> 120000 | F3: 45000 | G3: 35000 | H3: You will need to calculate April as it is needed for other budgets
A4: Add: Desired Ending Inventory | B4: =0.4*C3 -> 16000 | C4: =0.4*D3 -> 20000 | D4: =0.4*F3 -> 18000 | E4: =D4 -> 18000 | F4: =0.4*G3 -> 14000 | H4: Remember: this is 40% of the following month
A5: Total Needs | B5: =B3+B4 -> 46000 | C5: =C3+C4 -> 60000 | D5: =D3+D4 -> 68000 | E5: =E3+E4 -> 138000 | F5: =F3+F4 -> 59000
A6: Less: Beginning Inventory | B6: =0.4*B3 -> 12000 | C6: =B4 -> 16000 | D6: =C4 -> 20000 | E6: =B6 -> 12000 | F6: =D4 -> 18000 | H6: Beginning is previous month's ending
A7: Required Production | B7: =B5-B6 -> 34000 | C7: =C5-C6 -> 44000 | D7: =D5-D6 -> 48000 | E7: =E5-E6 -> 126000 | F7: =F5-F6 -> 41000

Sheet Direct Materials
B2: January | C2: February | D2: March | E2: Q1 | F2: April
A3: Production | B3: =Production!B7 -> 34000 | C3: =Production!C7 -> 44000 | D3: =Production!D7 -> 48000 | E3: =SUM(B3:D3) -> 126000 | F3: =Production!F7 -> 41000 | G3: You will need to calculate April as it is needed for other budgets
A4: Materials per pound (kg) | B4: 3 | C4: =B4 -> 3 | D4: =B4 -> 3 | E4: =B4 -> 3 | F4: =B4 -> 3
A5: Production Needs | B5: =B3*B4 -> 102000 | C5: =C3*C4 -> 132000 | D5: =D3*D4 -> 144000 | E5: =E3*E4 -> 378000 | F5: =F3*F4 -> 123000
A6: Add: Desired Ending Inventory | B6: =0.2*C5 -> 26400 | C6: =0.2*D5 -> 28800 | D6: =0.2*F5 -> 24600 | E6: =D6 -> 24600 | G6: Remember: this is 20% of the following month
A7: Total Needed | B7: =B5+B6 -> 128400 | C7: =C5+C6 -> 160800 | D7: =D5+D6 -> 168600 | E7: =E5+E6 -> 402600
A8: Less: Beginning Inventory | B8: =163200/8 -> 20400 | C8: =B6 -> 26400 | D8: =C6 -> 28800 | E8: =B8 -> 20400 | G8: Beginning is previous month's ending
A9: Materials to be Purchased | B9: =B7-B8 -> 108000 | C9: =C7-C8 -> 134400 | D9: =D7-D8 -> 139800 | E9: =E7-E8 -> 382200

Sheet Cash Payments
B2: January | C2: February | D2: March | E2: Q1
A3: AP Opening Balance | B3: 571200 | C3: 0 | D3: 0 | E3: =SUM(B3:D3) -> 571200 | F3: Remember to pay your opening balance sheet AP
A4: January Purchases
A5: 0.3 | B5: ='Direct Materials'!B9*$B$16*A5 -> 259200
A6: 0.7 | C6: ='Direct Materials'!B9*$B$16*A6 -> 604800
A7: February Purchases
A8: 0.3 | C8: ='Direct Materials'!C9*$B$16*A8 -> 322560
A9: 0.7 | D9: ='Direct Materials'!C9*$B$16*A9 -> 752640
A10: March Purchases
A11: 0.3 | D11: ='Direct Materials'!D9*$B$16*A11 -> 335520
A12: 0.7
A13: Total Cash Payments | B13: =SUM(B3:B12) -> 830400 | C13: =SUM(C3:C12) -> 927360 | D13: =SUM(D3:D12) -> 1088160 | E13: =SUM(B13:D13) -> 2845920
A16: Price per kg | B16: 8
A18: AP at end of Q1 | B18: ='Direct Materials'!D9*$B$16*A12 -> 782880 | F18: You will use this in your ending balance sheet

Sheet Direct Labor
B2: January | C2: February | D2: March | E2: Q1
A3: Units of Production | B3: =Production!B7 -> 34000 | C3: =Production!C7 -> 44000 | D3: =Production!D7 -> 48000 | E3: =SUM(B3:D3) -> 126000
A4: Direct Labor Time per Unit | B4: 2 | C4: =B4 -> 2 | D4: =B4 -> 2 | E4: =B4 -> 2
A5: Labor Hours Required | B5: =B3*B4 -> 68000 | C5: =C3*C4 -> 88000 | D5: =D3*D4 -> 96000 | E5: =E3*E4 -> 252000
A6: Hourly Wage Rate | B6: 6 | C6: =B6 -> 6 | D6: =B6 -> 6 | E6: =B6 -> 6
A7: Total Direct Labor Costs | B7: =B5*B6 -> 408000 | C7: =C5*C6 -> 528000 | D7: =D5*D6 -> 576000 | E7: =E5*E6 -> 1512000

Sheet Mfg OH
B2: January | C2: February | D2: March | E2: Q1
A3: Budgeted Direct Labor Hours | B3: ='Direct Labor'!B5 -> 68000 | C3: ='Direct Labor'!C5 -> 88000 | D3: ='Direct Labor'!D5 -> 96000 | E3: =SUM(B3:D3) -> 252000
A4: Variable Mfg. OH Rate | B4: 2 | C4: =B4 -> 2 | D4: =B4 -> 2 | E4: =B4 -> 2
A5: Variable Mfg. OH Costs | B5: =B3*B4 -> 136000 | C5: =C3*C4 -> 176000 | D5: =D3*D4 -> 192000 | E5: =E3*E4 -> 504000
A6: Fixed Mfg. OH Costs | B6: 225000 | C6: =B6 -> 225000 | D6: =B6 -> 225000 | E6: =SUM(B6:D6) -> 675000
A7: Total Mfg. OH Costs | B7: =B5+B6 -> 361000 | C7: =C5+C6 -> 401000 | D7: =D5+D6 -> 417000 | E7: =E5+E6 -> 1179000
A8: Less: Noncash Costs | B8: 35000 | C8: =B8 -> 35000 | D8: =B8 -> 35000 | E8: =SUM(B8:D8) -> 105000
A9: Cash Disbursements for Mfg. OH | B9: =B7-B8 -> 326000 | C9: =C7-C8 -> 366000 | D9: =D7-D8 -> 382000 | E9: =E7-E8 -> 1074000
B16: Qty | C16: Cost | D16: Total
A17: Finished Goods Inventory:
A18: Direct Materials (kg) | B18: ='Direct Materials'!B4 -> 3 | C18: ='Cash Payments'!B16 -> 8 | D18: =B18*C18 -> 24 | F18: Remember to let Excel do your calculations
A19: Direct Labor | B19: ='Direct Labor'!B4 -> 2 | C19: ='Direct Labor'!B6 -> 6 | D19: =B19*C19 -> 12
A20: Mfg. OH | B20: ='Direct Labor'!B4 -> 2 | C20: =E7/E3 -> 4.6785714 | D20: =B20*C20 -> 9.3571429
A21: Unit Product Cost | D21: =SUM(D18:D20) -> 45.357143
A23: Ending Inventory in Units | D23: =Production!D4 -> 18000
A24: Unit Product Cost | D24: =D21 -> 45.357143 | F24: Do NOT hard key numbers; use Excel
A25: Ending Finished Goods Inventory | D25: =D23*D24 -> 816428.57

Sheet Selling & Admin
B2: January | C2: February | D2: March | E2: Q1
A3: Budgeted Sales | B3: ='Sales Budget'!B3 -> 30000 | C3: ='Sales Budget'!C3 -> 40000 | D3: ='Sales Budget'!D3 -> 50000 | E3: =SUM(B3:D3) -> 120000
A4: Variable S&A Rate | B4: 2 | C4: =B4 -> 2 | D4: =B4 -> 2 | E4: =B4 -> 2
A5: Variable Expenses | B5: =B3*B4 -> 60000 | C5: =C3*C4 -> 80000 | D5: =D3*D4 -> 100000 | E5: =E3*E4 -> 240000
A6: Fixed S&A Expenses | B6: 100000 | C6: =B6 -> 100000 | D6: =B6 -> 100000 | E6: =SUM(B6:D6) -> 300000
A7: Total S&A Expenses | B7: =B5+B6 -> 160000 | C7: =C5+C6 -> 180000 | D7: =D5+D6 -> 200000 | E7: =E5+E6 -> 540000
A8: Less: Noncash Expenses | B8: 25000 | C8: =B8 -> 25000 | D8: =B8 -> 25000 | E8: =SUM(B8:D8) -> 75000
A9: Cash S&A Expenses | B9: =B7-B8 -> 135000 | C9: =C7-C8 -> 155000 | D9: =D7-D8 -> 175000 | E9: =E7-E8 -> 465000

Sheet Cash Budget
B2: January | C2: February | D2: March | E2: Q1
A3: Beginning Cash Balance | B3: 110000 | C3: =B20 -> 50600 | D3: =C20 -> 63740 | E3: =B3 -> 110000 | F3: January beginning balance comes from your opening balance sheet
A4: Add: Cash Collections | B4: ='Cash Collections'!B16 -> 1890000 | C4: ='Cash Collections'!C16 -> 2040000 | D4: ='Cash Collections'!D16 -> 2460000 | E4: =SUM(B4:D4) -> 6390000
A5: Total Cash Available | B5: =B3+B4 -> 2000000 | C5: =C3+C4 -> 2090600 | D5: =D3+D4 -> 2523740 | E5: =E3+E4 -> 6500000
A6: Less: Cash Disbursements
A7: Materials | B7: ='Cash Payments'!B13 -> 830400 | C7: ='Cash Payments'!C13 -> 927360 | D7: ='Cash Payments'!D13 -> 1088160 | E7: =SUM(B7:D7) -> 2845920
A8: Labor | B8: ='Direct Labor'!B7 -> 408000 | C8: ='Direct Labor'!C7 -> 528000 | D8: ='Direct Labor'!D7 -> 576000 | E8: =SUM(B8:D8) -> 1512000
A9: Mfg. OH | B9: ='Mfg OH'!B9 -> 326000 | C9: ='Mfg OH'!C9 -> 366000 | D9: ='Mfg OH'!D9 -> 382000 | E9: =SUM(B9:D9) -> 1074000
A10: S&A | B10: ='Selling & Admin'!B9 -> 135000 | C10: ='Selling & Admin'!C9 -> 155000 | D10: ='Selling & Admin'!D9 -> 175000 | E10: =SUM(B10:D10) -> 465000
A11: Equipment Purchase | B11: 300000 | C11: 0 | D11: 0 | E11: =SUM(B11:D11) -> 300000
A12: Dividend | B12: 0 | C12: 0 | D12: 150000 | E12: =SUM(B12:D12) -> 150000
A13: Total Disbursements | B13: =SUM(B7:B12) -> 1999400 | C13: =SUM(C7:C12) -> 1976360 | D13: =SUM(D7:D12) -> 2371160 | E13: =SUM(E7:E12) -> 6346920
A14: Excess/(Deficiency) | B14: =B5-B13 -> 600 | C14: =C5-C13 -> 114240 | D14: =D5-D13 -> 152580 | E14: =E5-E13 -> 153080
A15: Financing:
A16: Borrowing | B16: =IF(B14<50000,CEILING(50000-B14,5000),0) -> 50000 | C16: =IF(C14<50000,CEILING(50000-C14,5000),0) -> 0 | D16: =IF(D14<50000,CEILING(50000-D14,5000),0) -> 0 | E16: =SUM(B16:D16) -> 50000 | F16: Remember: this has to be in $5,000 increments
A17: Repayment | B17: 0 | C17: =IF(C14>=50000,MIN(B16-B17,FLOOR(MAX(C14-50000,0)/1.01,5000)),0) -> 50000 | D17: =IF(D14>=50000,MIN(B16-B17+C16-C17,FLOOR(MAX(D14-50000,0)/1.01,5000)),0) -> 0 | E17: =SUM(B17:D17) -> 50000 | F17: You have enough cash in February to pay back a large portion of your borrowing from January
A18: Interest | B18: =B17*0.01 -> 0 | C18: =C17*0.01 -> 500 | D18: =D17*0.01 -> 0 | E18: =SUM(B18:D18) -> 500 | F18: Remember: interest is calculated on the amount you pay back; we are using a 12% ANNUAL rate
A19: Total Financing | B19: =B16-B17-B18 -> 50000 | C19: =C16-C17-C18 -> -50500 | D19: =D16-D17-D18 -> 0 | E19: =SUM(B19:D19) -> -500
A20: Ending Cash Balance | B20: =B14+B19 -> 50600 | C20: =C14+C19 -> 63740 | D20: =D14+D19 -> 152580 | E20: =D20 -> 152580

Sheet Income Statement
A1: Traditional Format
A3: Sales | B3: ='Sales Budget'!E5 -> 7200000
A4: Less: Cost of Goods Sold | B4: =B18 -> 5438571.4
A5: Gross Margin | B5: =B3-B4 -> 1761428.6
A6: Less: SG&A Expenses | B6: ='Selling & Admin'!E7 -> 540000
A7: Less: Interest Expense | B7: ='Cash Budget'!E18 -> 500
A8: Net Income | B8: =B5-B6-B7 -> 1220928.6
A13: Supplemental Calculation: | C13: Remember to let Excel do the calculations; do not hard key numbers
A14: Cost of Beg. Finished Goods | B14: 540000 | C14: Comes from opening balance sheet
A15: Add: Cost of units produced | B15: =Production!E7*'Mfg OH'!D21 -> 5715000 | C15: This is your production needs x finished goods rate
A16: Equals: Cost of Goods Available for Sale | B16: =B14+B15 -> 6255000
A17: Less: Cost of Ending FG Inventory | B17: ='Mfg OH'!D25 -> 816428.57 | C17: You calculated your ending finished goods on the OH tab
A18: Equals: COGS | B18: =B16-B17 -> 5438571.4 | C18: This is your COGS for your income statement above

Sheet Balance Sheet
A2: Assets:
A3: Cash | B3: ='Cash Budget'!D20 -> 152580
A4: AR | B4: ='Cash Collections'!B18 -> 2580000
A5: Raw Materials Inventory | B5: ='Direct Materials'!D6*'Cash Payments'!B16 -> 196800 | C5: Remember: this is your direct materials ending inventory x raw material rate
A6: Finished Goods Inventory | B6: ='Mfg OH'!D25 -> 816428.57
A7: Total Current Assets | B7: =SUM(B3:B6) -> 3745808.6
A8: Net PP&E | B8: =B23 -> 1320000 | C8: See supplemental calculation below
A9: Total Assets | B9: =B7+B8 -> 5065808.6
A10: Liabilities & Stockholder's Equity
A11: Accounts Payable | B11: ='Cash Payments'!B18 -> 782880
A12: Total Liabilities | B12: =B11 -> 782880
A13: Common Stock | B13: 1500000
A14: Retained Earnings | B14: =B28 -> 2782928.6 | C14: See supplemental calculation below
A15: Total Liabilities & Stockholder's Equity | B15: =B12+B13+B14 -> 5065808.6
B16: =B15-B9 -> 0 | C16: check figure - Assets = Liabilities + Stockholders Equity
A19: Supplemental Calculations:
A20: PP&E Beginning Balance | B20: 1200000
A21: Additions for the year | B21: ='Cash Budget'!E11 -> 300000
A22: Less: Current Year Depreciation | B22: ='Mfg OH'!E8+'Selling & Admin'!E8 -> 180000
B23: =B20+B21-B22 -> 1320000
A25: Beg. Retained Earnings | B25: 1712000
A26: Add: Net Income | B26: ='Income Statement'!B8 -> 1220928.6
A27: Less: Dividends | B27: ='Cash Budget'!E12 -> 150000
A28: Ending Retained Earnings | B28: =B25+B26-B27 -> 2782928.6
