Workbook

Sheet Income Statement
B3: Actual 2016 | C3: Forecast 2017 | D3: YOY $ Variance
A4: Sales | B4: 2856000 | C4: 2941680 | D4: =C4-B4 -> 85680
A5: Less: Cost of Goods Sold | B5: 2284800 | C5: 2353344 | D5: =C5-B5 -> 68544
A6: Gross Margin | B6: =B4-B5 -> 571200 | C6: =C4-C5 -> 588336 | D6: =C6-B6 -> 17136
A7: Less: SG&A Expenses | B7: =244800+122400+122400+28560 -> 518160 | C7: =244800+122400+122400+34558 -> 524158 | D7: =C7-B7 -> 5998
A8: Net Income | B8: =B6-B7 -> 53040 | C8: =C6-C7 -> 64178 | D8: =C8-B8 -> 11138

Sheet Balance Sheet
A4: Assets: | B4: Actual 2016 | C4: Forecast 2017 | D4: YOY $ Variance
A5: Cash | B5: 20400 | C5: 124466 | D5: =C5-B5 -> 104066
A6: AR | B6: 388000 | C6: 322376 | D6: =C6-B6 -> -65624
A7: Inventory | B7: 826200 | C7: 588336 | D7: =C7-B7 -> -237864
A8: Current Assets | B8: =SUM(B5:B7) -> 1234600 | C8: =SUM(C5:C7) -> 1035178 | D8: =C8-B8 -> -199422
A9: Gross Book Value - Fixed Assets | B9: 826300 | C9: 926300 | D9: =C9-B9 -> 100000
A10: Accumulated Depreciation | B10: -595800 | C10: -718200 | D10: =C10-B10 -> -122400
A11: Net Book Value - Fixed Assets | B11: =B9+B10 -> 230500 | C11: =C9+C10 -> 208100 | D11: =C11-B11 -> -22400
A12: Total Assets | B12: =B8+B11 -> 1465100 | C12: =C8+C11 -> 1243278 | D12: =C12-B12 -> -221822
A16: Liabilities:
A17: Notes Payable | B17: 286000 | C17: 0 | D17: =C17-B17 -> -286000
A18: Accounts Payable | B18: 306000 | C18: 306000 | D18: =C18-B18 -> 0
A19: Accruals | B19: 77500 | C19: 77500 | D19: =C19-B19 -> 0
A20: Current Liabilities | B20: =SUM(B17:B19) -> 669500 | C20: =SUM(C17:C19) -> 383500 | D20: =C20-B20 -> -286000
A21: Mortgage - LT | B21: 36700 | C21: 36700 | D21: =C21-B21 -> 0
A22: Total Liabilities | B22: =B20+B21 -> 706200 | C22: =C20+C21 -> 420200 | D22: =C22-B22 -> -286000
A26: Stockholders' Equity:
A27: Common Stock | B27: 365000 | C27: 365000 | D27: =C27-B27 -> 0
A28: Retained Earnings | B28: 393900 | C28: 458078 | D28: =C28-B28 -> 64178
A29: Total Stockholders' Equity | B29: =B27+B28 -> 758900 | C29: =C27+C28 -> 823078 | D29: =C29-B29 -> 64178
A30: Total Liabilities & Stockholders' Equity | B30: =B22+B29 -> 1465100 | C30: =C22+C29 -> 1243278 | D30: =C30-B30 -> -221822

Sheet Statement of Cash Flows
B3: Actual 2016 | C3: Forecast 2017 | D3: YOY $ Variance
A4: Net Income | B4: 53040 | C4: 64178 | D4: =C4-B4 -> 11138
A5: Add: Sources of Funds (list individually) | B5: =530940-53040 -> 477900 | C5: =490066-C4 -> 425888 | D5: =C5-B5 -> -52012
A6: Total Sources of Funds | B6: =B4+B5 -> 530940 | C6: =C4+C5 -> 490066 | D6: =C6-B6 -> -40874
A8: Less: Uses of Funds (list individually) | B8: -539140 | C8: -386000 | D8: =C8-B8 -> 153140
A9: Total Uses of Funds | B9: =B8 -> -539140 | C9: =C8 -> -386000 | D9: =C9-B9 -> 153140
A11: Net Increase/(Decrease) in Cash | B11: =B6+B9 -> -8200 | C11: =C6+C9 -> 104066 | D11: =C11-B11 -> 112266
A12: Plus: Beginning Cash Balance | B12: 28600 | C12: =B13 -> 20400 | D12: =C12-B12 -> -8200
A13: Ending Cash Balance | B13: =B11+B12 -> 20400 | C13: =C11+C12 -> 124466 | D13: =C13-B13 -> 104066

Sheet Ratio Comparisons & Analysis
A1: Paley Products
A2: Ratio Analysis
B4: Industry | C4: Paley Products
A5: Ratio | B5: Average | C5: 2017 | D5: 2016 | E5: 2015 | F5: 2014 | G5: Analysis Comments
A6: Current Ratio = Current Assets/Current Liabilities | B6: 2.7 | C6: ='Balance Sheet'!C8/'Balance Sheet'!C20 -> 2.6992907 | D6: ='Balance Sheet'!B8/'Balance Sheet'!B20 -> 1.8440627 | E6: 2.6 | F6: 4.2 | G6: Paley has experienced a significant decline in their current ratio YOY. Currently, they do not have enough current assets to cover their current liabilities. In comparison to their industry, they are lagging and this raises concerns about their liquidity.The forecast shows significant improvement if they can achieve it.
A7: Quick Ratio = | B7: 1 | C7: =('Balance Sheet'!C8-'Balance Sheet'!C7)/'Balance Sheet'!C20 -> 1.1651682 | D7: =('Balance Sheet'!B8-'Balance Sheet'!B7)/'Balance Sheet'!B20 -> 0.61000747 | E7: 1 | F7: 2.1 | G7: Paley's quick ratio is forecast to rebound to 1.2 in 2017 from a low of 0.6 in 2016, moving back above the industry average of 1.0 for the first time since 2015. This means the company would once again have enough cash and receivables alone (without relying on inventory) to cover its current liabilities, which should ease the bank's liquidity concerns if the plan is achieved. Until then, the 2016 result (0.6) shows Paley was significantly short of liquid assets relative to peers.
A8: Inventory Turnover = | B8: 7 | C8: ='Income Statement'!C5/'Balance Sheet'!C7 -> 4 | D8: ='Income Statement'!B5/'Balance Sheet'!B7 -> 2.7654321 | E8: 4.3 | F8: 6.9 | G8: Inventory turnover is projected to improve to 4.0x in 2017, up from a low of 2.8x in 2016, but it remains far below the industry average of 7.0x and below Paley's own 2014 level of 6.9x. Even with the planned improvement, Paley is still turning inventory roughly half as often as its competitors, meaning cash continues to sit in inventory longer than it should and working capital is being used inefficiently.
A9: DSO = | B9: 32 | C9: =('Balance Sheet'!C6)/'Income Statement'!C4*365 -> 40.000014 | D9: =('Balance Sheet'!B6)/'Income Statement'!B4*365 -> 49.586835 | E9: 37 | F9: 34 | G9: Days sales outstanding is forecast to improve to 40 days in 2017 from 50 days in 2016, but this is still well above the industry average of 32 days and above Paley's 2014 level of 34 days. Slower collections tie up cash that could otherwise be used to pay down debt or fund operations, and the gap versus the industry suggests Paley's credit and collections practices remain looser than its peers'.
A10: DPO = | B10: NA | C10: =('Balance Sheet'!C18)/'Income Statement'!C5*365 -> 47.460125 | D10: =('Balance Sheet'!B18)/'Income Statement'!B5*365 -> 48.883929 | E10: =155000/2203200*365 -> 25.678558 | F10: =98000/2121600*365 -> 16.859917 | G10: DPO has risen sharply, from about 17 days in 2014 to 49 days in 2016, as Paley increasingly stretched payments to suppliers to help fund its growing inventory and receivables; the 2017 forecast of 47 days keeps DPO near this elevated level. No industry figure is available for comparison, but a DPO this much higher than DSO (40 days) signals reliance on supplier financing that could strain vendor relationships or cause Paley to lose early-payment discounts if it isn't managed carefully.
A11: Gross Profit Margin = | B11: NA | C11: ='Income Statement'!C6/'Income Statement'!C4 -> 0.2 | D11: ='Income Statement'!B6/'Income Statement'!B4 -> 0.2 | E11: =550800/2754000 -> 0.2 | F11: =530400/2652000 -> 0.2 | G11: Gross profit margin has held essentially flat at 20.0% every year from 2014 through the 2017 forecast, showing Paley has maintained its markup on goods sold despite rising input and labor costs. Because this ratio has not declined, it indicates that Paley's shrinking profitability over the years is coming from expenses below the gross profit line (G&A, depreciation, and miscellaneous costs), not from pricing or production cost pressure itself.
A12: Net Profit Margin = | B12: NA | C12: ='Income Statement'!C8/'Income Statement'!C4 -> 0.021816785 | D12: ='Income Statement'!B8/'Income Statement'!B4 -> 0.018571429 | E12: =90155/2754000 -> 0.03273602 | F12: =132600/2652000 -> 0.05 | G12: Net profit margin is forecast to recover to about 2.2% in 2017 from a low of 1.8% in 2016, but it remains far below the roughly 4.5% margin management should be targeting to match industry norms (per the case's industry profit-margin benchmark) and well under Paley's own 5.0% margin in 2014. Operating expenses have grown faster than sales for several years, and even the improvement plan only partially closes that gap.
A13: Return on Assets = | B13: 0.117 | C13: ='Income Statement'!C8/'Balance Sheet'!C12 -> 0.051619992 | D13: ='Income Statement'!B8/'Balance Sheet'!B12 -> 0.036202307 | E13: 0.084 | F13: 0.158 | G13: Return on assets is expected to improve to about 5.2% in 2017 from 3.6% in 2016, but this is still less than half the industry average of 11.7% and far below Paley's 2014 return of 15.8%. Total assets have roughly doubled since 2014 while profitability has not kept pace, meaning each dollar invested in the business is generating substantially less profit than it used to, or than a typical industry competitor.
A14: Return on Equity = | B14: 0.234 | C14: ='Income Statement'!C8/'Balance Sheet'!C29 -> 0.077973169 | D14: ='Income Statement'!B8/'Balance Sheet'!B29 -> 0.069890631 | E14: 0.12 | F14: 0.2 | G14: Return on equity is forecast to rise to about 7.8% in 2017 from 7.0% in 2016, an improvement but still well short of the 23.4% industry average and Paley's own 20.0% return in 2014. Shareholders are earning a much lower return on their investment than industry peers, which could make it harder for Paley to attract additional equity capital if it needs it in the future.
A15: Debt Ratio = | B15: 0.5 | C15: ='Balance Sheet'!C22/'Balance Sheet'!C12 -> 0.33797751 | D15: ='Balance Sheet'!B22/'Balance Sheet'!B12 -> 0.48201488 | E15: 0.33 | F15: 0.22 | G15: The debt ratio is projected to fall to about 33.8% in 2017 as bank debt is paid off, a sizable improvement from 48% in 2016 and back below the 50% industry average. This directly reflects the plan to use improved cash flow to retire the bank line of credit and would materially reduce Paley's financial risk if achieved.
A16: Debt/Equity Ratio = | B16: NA | C16: ='Balance Sheet'!C22/'Balance Sheet'!C29 -> 0.5105227 | D16: ='Balance Sheet'!B22/'Balance Sheet'!B29 -> 0.93055739 | E16: =(314000+40800)/(365000+353300) -> 0.49394403 | F16: =(147000+45000)/(365000+283600) -> 0.2960222 | G16: Debt-to-equity climbed steadily from about 0.3 in 2014 to 0.9 in 2016 as bank borrowing increased to fund growth, but is forecast to reverse to roughly 0.5 in 2017 if the bank debt is paid off as planned. This would bring leverage back closer to 2015 levels; achieving it, however, depends entirely on hitting the working-capital targets (DSO and inventory turnover) built into the improvement plan.

Sheet Questions & Analysis Comments
A1: Questions | B1: Comments/Analysis
A2: Will the company be able to pay off their debt? | B2: Yes, if Paley executes its 2017 improvement plan. The forecast shows enough cash generated from operations — mainly by shrinking inventory and accounts receivable rather than from profit growth alone — to fully retire the $286,000 in bank notes payable, fund $100,000 of capital expenditures, and still end the year with about $124,000 in cash (up from roughly $20,000). This outcome is not guaranteed, though: it requires Paley to simultaneously grow sales 3%, hold expenses flat, and reverse several years of deteriorating working capital performance (getting inventory turnover from 2.8x to 4.0x and DSO from 50 to 40 days) all in a single year.
A3: Is the company facing any problems or issues? | B3: Yes. The underlying issue is that working capital efficiency has steadily worsened since 2014 — inventory and receivables have grown much faster than sales — while operating expenses (G&A, depreciation, and miscellaneous costs) have also outpaced revenue growth. Gross margin has stayed flat at 20%, so the profit decline is coming entirely from below the gross-profit line. This combination has forced Paley to rely on increasing amounts of bank debt and stretched payables to fund operations, which is what pushed the current ratio below the bank's 2.0 covenant and triggered the loan review.
A4: How does the company compare to their peers in their industry? | B4: Paley trails the computer component manufacturing industry on nearly every ratio in 2016: its current ratio (1.8) and quick ratio (0.6) are both well below the industry's 2.7 and 1.0; inventory turnover (2.8x) is less than half the industry's 7.0x; collections take longer (50 days vs. 32); and profitability is a fraction of peers' (ROA 3.6% vs. 11.7%; ROE 7.0% vs. 23.4%). The one exception is the debt ratio, where Paley (48%) is actually slightly below the industry average (50%), though this is a smaller consolation given how weak the liquidity and profitability metrics are by comparison. Even under the 2017 forecast, Paley closes some of the gap (current ratio near 2.7, gross margin at 20%) but likely still lags peers on turnover and profitability.
A5: Do you see any trends or areas of concern from your analysis of the company’s financials? | B5: The clear trend is steady deterioration across almost every category from 2014 to 2016: current ratio fell from 4.2 to 1.8, inventory turnover dropped from 6.9x to 2.8x, DSO rose from 34 to 50 days, and ROA fell from 15.8% to 3.6%, even as total assets and revenue grew. This pattern shows growth being funded by increasingly inefficient use of working capital (rising inventory and receivables) and by mounting bank debt rather than by improved profitability — exactly the dynamic that caused the loan covenant violation. The 2017 forecast shows meaningful improvement is achievable, but because it reverses several years of neglect in one year, it should be treated as an aggressive target that needs close monitoring rather than an assured outcome.
